dexhub/__init__.py
dexhub/bridge.py
dexhub/dex.py
dexhub/abi/__init__.py
dexhub/abi/arbitrum_abi.py
dexhub/abi/avax_abi.py
dexhub/abi/dfk_abi.py
dexhub/abi/eth_abi.py
dexhub/abi/klay_abi.py
dexhub/address/__init__.py
dexhub/address/arbitrum_address.py
dexhub/address/avax_address.py
dexhub/address/dfk_address.py
dexhub/address/eth_address.py
dexhub/address/klay_address.py
dexhub/address/polygon_address.py
dexhub/interface/__init__.py
dexhub/interface/joe.py
dexhub/util/__init__.py
dexhub/util/helper.py
dexhub/util/joe_v2.py
dexhub-0.8.0.dist-info/LICENSE
dexhub-0.8.0.dist-info/METADATA
dexhub-0.8.0.dist-info/WHEEL
dexhub-0.8.0.dist-info/top_level.txt
dexhub-0.8.0.dist-info/RECORD
