Metadata-Version: 2.1
Name: dexhub
Version: 0.8.0
Summary: dex connector
Home-page: https://github.com/elmtlab/aurum
Author: elmtlab
Author-email: elmtlab@outlook.com
License: UNKNOWN
Platform: UNKNOWN
Classifier: Programming Language :: Python :: 3
Classifier: Operating System :: OS Independent
Requires-Dist: web3
